tableswift/__init__.py
tableswift/config.py
tableswift/core.py
tableswift/promptsTemplate.py
tableswift/run_wrangler.py
tableswift/code_generator/__init__.py
tableswift/code_generator/base_generator.py
tableswift/code_generator/python_generator.py
tableswift/code_generator/sql_generator.py
tableswift/llm_pr/llmpr.py
tableswift/logic/codegen.py
tableswift/logic/execution.py
tableswift/logic/labeling.py
tableswift/utils/__init__.py
tableswift/utils/contants.py
tableswift/utils/data_utils.py
tableswift/utils/formatter_utils.py
tableswift/utils/function_utils.py
tableswift/utils/other_utils.py
tableswift-0.1.4.dist-info/METADATA
tableswift-0.1.4.dist-info/WHEEL
tableswift-0.1.4.dist-info/top_level.txt
tableswift-0.1.4.dist-info/RECORD
