Metadata-Version: 2.4
Name: tableswift
Version: 0.1.4
Summary: Data wrangling framework with LLM using code generation
Author-email: Effy Li <effylix@gmail.com>
Requires-Python: >=3.8
Requires-Dist: numpy
Requires-Dist: regex
Requires-Dist: fraction
Requires-Dist: scikit-learn
Requires-Dist: Levenshtein
Requires-Dist: pyproj
Requires-Dist: beautifulsoup4
Requires-Dist: geopy
Requires-Dist: ummalqura
Requires-Dist: mgrs
Requires-Dist: pytz
Requires-Dist: datetime
Requires-Dist: roman
Requires-Dist: pyspellchecker
Requires-Dist: nltk
Requires-Dist: openai
Requires-Dist: together
Requires-Dist: instructor
Requires-Dist: ollama
Requires-Dist: pydantic
